screen2c/__init__.py
screen2c-0.1.1.dist-info/LICENSE
screen2c-0.1.1.dist-info/METADATA
screen2c-0.1.1.dist-info/WHEEL
screen2c-0.1.1.dist-info/top_level.txt
screen2c-0.1.1.dist-info/RECORD
