Metadata-Version: 2.1
Name: screen2c
Version: 0.1.1
Summary: An interface to I2C screens with a PCF8574 backpack
Home-page: https://github.com/GingerIndustries/screen2c
Author: Denis Pleic
Maintainer: GingerIndustries
License: UNKNOWN
Project-URL: Documentation, https://screen2c.readthedocs.io
Project-URL: Original code, https://gist.github.com/DenisFromHR/cc863375a6e19dce359d
Platform: UNKNOWN
Classifier: Programming Language :: Python :: 3
Classifier: License :: OSI Approved :: MIT License
Classifier: Operating System :: OS Independent
Requires-Python: >=3.6
Requires-Dist: smbus
